ReferenceFinder/ReferenceUtils.py
ReferenceFinder/__init__.py
referencefinder-1.dist-info/METADATA
referencefinder-1.dist-info/WHEEL
referencefinder-1.dist-info/top_level.txt
referencefinder-1.dist-info/RECORD
