Metadata-Version: 2.1
Name: referencefinder
Version: 1
Summary: this is basic tools for finding reference in papers 
Home-page: https://github.com/esafb52/reference_finder
Author: masiha ahmadi
Author-email: esafb@gmail.com
License: GPL
Platform: UNKNOWN
